<?xml version='1.0' encoding='utf-8'?><m:page id='e3115bc0-00c6-4191-8ee2-c0fe2c51b9d4' xmlns='http://www.w3.org/1999/xhtml' title='Exam_Schedule' class='layout-atlas layout-atlas-responsive-default' xmlns:m='http://schemas.mendix.com/forms/1.0'><m:layouts><m:layout path='Atlas_UI_Resources/Atlas_Default.layout.xml'></m:layout></m:layouts><m:arguments><m:argument parameterName='079cc77a-460a-5244-939e-24b2f993e6ec'><div data-mendix-id='8_0' data-mendix-type='mxui.widget.ReactWidgetWrapper' data-mendix-props='"widgetTree":[{"widget":"Title","widgetId":"8_0","props":{"name":"title1","caption":{"$type":"ExpressionProperty","expression":{"expr":{"type":"variable","variable":"pageTitle"},"args":{}},"friendlyId":"EventApplication.Exam_Schedule.title1"},"class":"mx-name-title1"}}]'></div><div data-mendix-id='8_1' data-mendix-type='mxui.widget.ReactWidgetWrapper' data-mendix-props='"widgetTree":[{"widget":"Div","widgetId":"8_1","props":{"name":"layoutGrid1","class":"mx-name-layoutGrid1 mx-layoutgrid mx-layoutgrid-fluid container-fluid","content":[{"widget":"Div","widgetId":"8_2","props":{"name":"","class":"row","content":[{"widget":"Div","widgetId":"8_3","props":{"name":"","class":"col-md-12 col-sm-12 col-xs-12","content":[{"widget":"Container","widgetId":"8_4","props":{"name":"divContainer1","renderMode":"div","onClick":null,"content":[{"widget":"Div","widgetId":"8_5","props":{"name":"layoutGrid2","class":"mx-name-layoutGrid2 mx-layoutgrid mx-layoutgrid-fluid","content":[{"widget":"Div","widgetId":"8_6","props":{"name":"","class":"row","content":[{"widget":"Div","widgetId":"8_7","props":{"name":"","class":"col-md-3 col-sm-12 col-xs-12","content":[{"widget":"Text","widgetId":"8_8","props":{"name":"dynamicText1","caption":{"$type":"DynamicTextProperty","template":{"elements":["Subject"],"friendlyId":"EventApplication.Exam_Schedule.dynamicText1"}},"renderMode":"span","class":"mx-name-dynamicText1"}}]}},{"widget":"Div","widgetId":"8_9","props":{"name":"","class":"col-md-3 col-sm-12 col-xs-12","content":[{"widget":"Text","widgetId":"8_10","props":{"name":"dynamicText2","caption":{"$type":"DynamicTextProperty","template":{"elements":["Date"],"friendlyId":"EventApplication.Exam_Schedule.dynamicText2"}},"renderMode":"span","class":"mx-name-dynamicText2"}}]}},{"widget":"Div","widgetId":"8_11","props":{"name":"","class":"col-md-3 col-sm-12 col-xs-12","content":[{"widget":"Text","widgetId":"8_12","props":{"name":"dynamicText3","caption":{"$type":"DynamicTextProperty","template":{"elements":["Time"],"friendlyId":"EventApplication.Exam_Schedule.dynamicText3"}},"renderMode":"span","class":"mx-name-dynamicText3"}}]}},{"widget":"Div","widgetId":"8_13","props":{"name":"","class":"col-md-3 col-sm-12 col-xs-12","content":[{"widget":"Text","widgetId":"8_14","props":{"name":"dynamicText4","caption":{"$type":"DynamicTextProperty","template":{"elements":["Hall No"],"friendlyId":"EventApplication.Exam_Schedule.dynamicText4"}},"renderMode":"span","class":"mx-name-dynamicText4"}}]}}]}}]}}],"class":"mx-name-divContainer1"}}]}}]}}]}}]'></div><div data-mendix-id='8_15' data-mendix-type='mxui.widget.ReactWidgetWrapper' data-mendix-props='"widgetTree":[{"widget":"Container","widgetId":"8_15","props":{"name":"divContainer2","renderMode":"div","onClick":null,"content":[{"widget":"Div","widgetId":"8_16","props":{"name":"layoutGrid3","class":"mx-name-layoutGrid3 mx-layoutgrid mx-layoutgrid-fluid container-fluid","content":[{"widget":"Div","widgetId":"8_17","props":{"name":"","class":"row","content":[{"widget":"Div","widgetId":"8_18","props":{"name":"","class":"col-md-3 col-sm-12 col-xs-12","content":[]}},{"widget":"Div","widgetId":"8_19","props":{"name":"","class":"col-md-3 col-sm-12 col-xs-12","content":[]}},{"widget":"Div","widgetId":"8_20","props":{"name":"","class":"col-md-3 col-sm-12 col-xs-12","content":[]}},{"widget":"Div","widgetId":"8_21","props":{"name":"","class":"col-md-3 col-sm-12 col-xs-12","content":[]}}]}}]}}],"class":"mx-name-divContainer2"}}]'></div></m:argument></m:arguments></m:page>